geny_gmtool/__init__.py
geny_gmtool/g_error.py
geny_gmtool/genygmtool.py
geny_gmtool/genymotion_model.py
geny_gmtool/thread_timer.py
geny_gmtool-0.0.7.dist-info/LICENSE
geny_gmtool-0.0.7.dist-info/METADATA
geny_gmtool-0.0.7.dist-info/WHEEL
geny_gmtool-0.0.7.dist-info/top_level.txt
geny_gmtool-0.0.7.dist-info/RECORD
