Metadata-Version: 2.1
Name: geny-gmtool
Version: 0.0.7
Summary: Gmtool use python to get
Author-email: Barry Allen <2420615378@qq.com>
License: Copyright (c) 2022 zhanghao19920218        
Project-URL: Homepage, https://github.com/zhanghao19920218/genymotion_gmtool
Project-URL: Bug Tracker, https://github.com/zhanghao19920218/genymotion_gmtool/issues
Classifier: Programming Language :: Python :: 3
Classifier: License :: OSI Approved :: MIT License
Classifier: Operating System :: OS Independent
Requires-Python: >=3.7
License-File: LICENSE
